Metadata-Version: 1.0
Name: diff-distributions-types
Version: 1.3
Summary: Gaussian distributions
Home-page: UNKNOWN
Author: Vishakha Tandon
Author-email: garitandon94@gmail.com
License: UNKNOWN
Platform: UNKNOWN
